adsonai_sdk/__init__.py
adsonai_sdk/client.py
adsonai_sdk/exceptions.py
adsonai_sdk/models.py
adsonai_sdk/__pycache__/__init__.cpython-313.pyc
adsonai_sdk/__pycache__/client.cpython-313.pyc
adsonai_sdk/__pycache__/exceptions.cpython-313.pyc
adsonai_sdk/__pycache__/models.cpython-313.pyc
warbler_adsonai-2.0.3.dist-info/METADATA
warbler_adsonai-2.0.3.dist-info/WHEEL
warbler_adsonai-2.0.3.dist-info/top_level.txt
warbler_adsonai-2.0.3.dist-info/RECORD
