Metadata-Version: 2.4
Name: warbler_adsonai
Version: 2.0.3
Summary: Python SDK for AdsonAI contextual advertising platform
Home-page: https://github.com/adsonai/adsonai-python-sdk
Author: AdsonAI Team
Author-email: AdsonAI Team <support@adsonai.com>
License: MIT
Project-URL: Homepage, https://adsonai.com
Project-URL: Documentation, https://docs.adsonai.com
Project-URL: Repository, https://github.com/adsonai/adsonai-python-sdk
Project-URL: Bug Tracker, https://github.com/adsonai/adsonai-python-sdk/issues
Keywords: advertising,ai,llm,contextual,ads,monetization
Platform: any
Classifier: Development Status :: 4 - Beta
Classifier: Intended Audience :: Developers
Classifier: License :: OSI Approved :: MIT License
Classifier: Operating System :: OS Independent
Classifier: Programming Language :: Python :: 3
Classifier: Programming Language :: Python :: 3.7
Classifier: Programming Language :: Python :: 3.8
Classifier: Programming Language :: Python :: 3.9
Classifier: Programming Language :: Python :: 3.10
Classifier: Programming Language :: Python :: 3.11
Classifier: Topic :: Software Development :: Libraries :: Python Modules
Requires-Python: >=3.7
Requires-Dist: httpx>=0.24.0
Provides-Extra: dev
Requires-Dist: pytest>=6.0; extra == "dev"
Requires-Dist: pytest-asyncio>=0.14.0; extra == "dev"
Requires-Dist: pytest-mock>=3.0; extra == "dev"
Requires-Dist: black>=21.0; extra == "dev"
Requires-Dist: flake8>=3.8; extra == "dev"
Requires-Dist: mypy>=0.800; extra == "dev"
Dynamic: author
Dynamic: home-page
Dynamic: platform
Dynamic: requires-python
